google_spreadsheets_fdw/__init__.py
google_spreadsheets_fdw-1.0.3.dist-info/LICENSE
google_spreadsheets_fdw-1.0.3.dist-info/METADATA
google_spreadsheets_fdw-1.0.3.dist-info/WHEEL
google_spreadsheets_fdw-1.0.3.dist-info/top_level.txt
google_spreadsheets_fdw-1.0.3.dist-info/RECORD
