Metadata-Version: 2.1
Name: google_spreadsheets_fdw
Version: 1.0.3
Summary: Multicorn-based PostgreSQL foreign data wrapper for Google Spreadsheets
Home-page: https://github.com/TheDeadJoe/google_spreadsheets_fdw
Author: TheDeadJoe
Classifier: Programming Language :: Python :: 3.5
Classifier: License :: OSI Approved :: MIT License
Classifier: Operating System :: OS Independent
License-File: LICENSE
Requires-Dist: gspread <4.0.0,>=3.6.0
Requires-Dist: multicorn <3.0.0,>=1.4.0
Requires-Dist: oauth2client <5.0.0,==4.1.3
